README.md
setup.py
aca/__init__.py
aca/aca.py
aca/stdlib.aca
acalang.egg-info/PKG-INFO
acalang.egg-info/SOURCES.txt
acalang.egg-info/dependency_links.txt
acalang.egg-info/entry_points.txt
acalang.egg-info/top_level.txt