Metadata-Version: 2.1
Name: acalang
Version: 0.3.0
Summary: Aca, a functional programming language, and shitty toy
Home-page: https://github.com/anqurvanillapy/acalang
Author: AnqurVanillapy
Author-email: anqurvanillapy@gmail.com
License: MIT
Platform: UNKNOWN
Classifier: Programming Language :: Python :: 3
Classifier: License :: OSI Approved :: MIT License
Classifier: Operating System :: OS Independent
